IndexAns/IndexAns.py
IndexAns/__init__.py
IndexAns-0.3.dist-info/LICENSE
IndexAns-0.3.dist-info/METADATA
IndexAns-0.3.dist-info/WHEEL
IndexAns-0.3.dist-info/top_level.txt
IndexAns-0.3.dist-info/RECORD
