Metadata-Version: 2.1
Name: IndexAns
Version: 0.3
Summary: UNKNOWN
Home-page: UNKNOWN
Author: Karigor
Author-email: 
License: MIT
Platform: UNKNOWN
Classifier: Programming Language :: Python :: 3
Classifier: License :: OSI Approved :: MIT License
Classifier: Operating System :: OS Independent
Requires-Dist: scikit-learn
Requires-Dist: scipy
